{
  "knownAssemblies": [
    { "name": "RestaurantApp" },
    { "name": "FreshMvvm" },
    {
      "name": "DLToolkit.Forms.Controls.FlowListView",
      "types": null
    },
    {
      "name": "UXDivers.Artina.Shared",
      "types": null
    }, 
     {
      "name": "ImageCircle.Forms.Plugin.Abstractions",
      "types": null
    }, 

    { "name": "RestaurantApp.Pages" },
    { "name": "RestaurantApp.Forms" },
    { "name": "RestaurantApp.Core" },
    { "name": "RestaurantApp.Data" },
    { "name": "RestaurantApp.Converters" },
    { "name": "RestaurantApp.UserControls" }
   
  ]
}